gencov/__init__.py
gencov/__main__.py
gencov/config.py
gencov/cov_util.py
gencov/gtf_util.py
gencov/heatmaps_array.py
gencov/loci_util.py
gencov/seq_util.py
gencov/umap_util.py
gencov/util.py
gencov/io/__init__.py
gencov/io/config.py
gencov/io/loci.py
gencov/io/sequence.py
gencov/io/signal.py
gencov/io/signal_c.py
gencov/io/signal_mod.py
gencov/io/signal_std.py
gencov/io/util.py
gencov/io/bin/libbigwig/.environmentLinux.yaml
gencov/io/bin/libbigwig/.gitignore
gencov/io/bin/libbigwig/.travis.yml
gencov/io/bin/libbigwig/CMakeLists.txt
gencov/io/bin/libbigwig/Doxyfile
gencov/io/bin/libbigwig/LICENSE
gencov/io/bin/libbigwig/Makefile
gencov/io/bin/libbigwig/README.md
gencov/io/bin/libbigwig/bigWig.h
gencov/io/bin/libbigwig/bigWigIO.h
gencov/io/bin/libbigwig/bwCommon.h
gencov/io/bin/libbigwig/bwRead.c
gencov/io/bin/libbigwig/bwRead.o
gencov/io/bin/libbigwig/bwRead.pico
gencov/io/bin/libbigwig/bwStats.c
gencov/io/bin/libbigwig/bwStats.o
gencov/io/bin/libbigwig/bwStats.pico
gencov/io/bin/libbigwig/bwValues.c
gencov/io/bin/libbigwig/bwValues.h
gencov/io/bin/libbigwig/bwValues.o
gencov/io/bin/libbigwig/bwValues.pico
gencov/io/bin/libbigwig/bwWrite.c
gencov/io/bin/libbigwig/bwWrite.o
gencov/io/bin/libbigwig/bwWrite.pico
gencov/io/bin/libbigwig/io.c
gencov/io/bin/libbigwig/io.o
gencov/io/bin/libbigwig/io.pico
gencov/io/bin/libbigwig/libBigWig.a
gencov/io/bin/libbigwig/libBigWig.so
gencov/io/bin/libbigwig/.github/workflows/build.yml
gencov/io/bin/samtools/bin/ace2sam
gencov/io/bin/samtools/bin/blast2sam.pl
gencov/io/bin/samtools/bin/bowtie2sam.pl
gencov/io/bin/samtools/bin/export2sam.pl
gencov/io/bin/samtools/bin/fasta-sanitize.pl
gencov/io/bin/samtools/bin/interpolate_sam.pl
gencov/io/bin/samtools/bin/maq2sam-long
gencov/io/bin/samtools/bin/maq2sam-short
gencov/io/bin/samtools/bin/md5fa
gencov/io/bin/samtools/bin/md5sum-lite
gencov/io/bin/samtools/bin/novo2sam.pl
gencov/io/bin/samtools/bin/plot-ampliconstats
gencov/io/bin/samtools/bin/plot-bamstats
gencov-0.0.16.dist-info/METADATA
gencov-0.0.16.dist-info/WHEEL
gencov-0.0.16.dist-info/licenses/LICENSE
gencov-0.0.16.dist-info/RECORD
