Metadata-Version: 2.1
Name: gencov
Version: 0.0.16
Summary: Process genomic data
Project-URL: Homepage, https://github.com/ajgouhier/gencov
Author-email: Arthur Gouhier <ajgouhier@gmail.com>
License: MIT
License-File: LICENSE
Classifier: License :: OSI Approved :: MIT License
Classifier: Operating System :: OS Independent
Classifier: Programming Language :: Python :: 3
Requires-Python: >=3.9
Requires-Dist: matplotlib>=3
Requires-Dist: numpy>=1
Requires-Dist: pandas>=1
Requires-Dist: umap-learn>=0
